.gitignore
LICENSE
README.md
setup.py
pgrok/__init__.py
pgrok/exception.py
pgrok/pgrok.py
pgrok/tools.py
pgrok.egg-info/PKG-INFO
pgrok.egg-info/SOURCES.txt
pgrok.egg-info/dependency_links.txt
pgrok.egg-info/entry_points.txt
pgrok.egg-info/top_level.txt
tests/__init__.py
tests/test_pgrok.py