Metadata-Version: 2.1
Name: pgrok
Version: 0.1.0
Summary: Python client for interacting with Pgrok!
Home-page: https://github.com/sandyz1000/pgrok-py
Author: Sandip Dey
Author-email: sandip.dey1988@yahoo.com
License: Apache License
Platform: UNKNOWN
Requires-Python: >=3.5
